scp_infer/__init__.py
scp_infer/adata/__init__.py
scp_infer/adata/filter_adata.py
scp_infer/adata/plot_adata.py
scp_infer/eval/__init__.py
scp_infer/eval/bio_eval.py
scp_infer/eval/eval_manager.py
scp_infer/eval/graph_eval.py
scp_infer/eval/sim_eval.py
scp_infer/eval/stat_eval.py
scp_infer/inference/__init__.py
scp_infer/inference/inference_method.py
scp_infer/inference/avici/__init__.py
scp_infer/inference/avici/avici_imp.py
scp_infer/inference/bicycle/__init__.py
scp_infer/inference/bicycle/bicycle_imp.py
scp_infer/inference/dcdi/__init__.py
scp_infer/inference/dcdi/dcdi_imp.py
scp_infer/inference/dcdi/dcdi_load.py
scp_infer/inference/gies/__init__.py
scp_infer/inference/gies/gies_imp.py
scp_infer/inference/grnboost2/__init__.py
scp_infer/inference/grnboost2/grnboost2_imp.py
scp_infer/inference/sdcd/__init__.py
scp_infer/inference/sdcd/sdcd_imp.py
scp_infer/thirdparty/arboreto_local/__init__.py
scp_infer/thirdparty/arboreto_local/algo.py
scp_infer/thirdparty/arboreto_local/core.py
scp_infer/thirdparty/arboreto_local/utils.py
scp_infer/thirdparty/bicycle_local/__init__.py
scp_infer/thirdparty/bicycle_local/callbacks.py
scp_infer/thirdparty/bicycle_local/dictlogger.py
scp_infer/thirdparty/bicycle_local/model.py
scp_infer/thirdparty/bicycle_local/model_eval.py
scp_infer/thirdparty/bicycle_local/nodags_files/llc.py
scp_infer/thirdparty/bicycle_local/nodags_files/nodags.py
scp_infer/thirdparty/bicycle_local/nodags_files/notears.py
scp_infer/thirdparty/bicycle_local/nodags_files/utils.py
scp_infer/thirdparty/bicycle_local/nodags_files/datagen/generateDataset.py
scp_infer/thirdparty/bicycle_local/nodags_files/datagen/graph.py
scp_infer/thirdparty/bicycle_local/nodags_files/datagen/structuralModels.py
scp_infer/thirdparty/bicycle_local/nodags_files/datagen/torchDataset.py
scp_infer/thirdparty/bicycle_local/nodags_files/models/functions.py
scp_infer/thirdparty/bicycle_local/nodags_files/models/resblock.py
scp_infer-0.0.1.dist-info/licenses/LICENSE.md
scp_infer-0.0.1.dist-info/METADATA
scp_infer-0.0.1.dist-info/WHEEL
scp_infer-0.0.1.dist-info/top_level.txt
scp_infer-0.0.1.dist-info/RECORD
