Metadata-Version: 2.4
Name: scp_infer
Version: 0.0.1
Summary: Utility for applying causal inference algorithms perturbed single-cell gene exression data
Author-email: "Jan L. Sprengel" <janlsprengel@gmail.com>
License-Expression: MIT
Project-URL: Homepage, https://github.com/velten-group/scp_infer
Project-URL: Issues, https://github.com/velten-group/scp_infer/issues
Classifier: Programming Language :: Python :: 3
Classifier: Operating System :: OS Independent
Requires-Python: >=3.11
License-File: LICENSE.md
Dynamic: license-file
